[
    {
        "name": "JetID_Run3_Prompt2022CDE_TightLeptonVeto_AK4PFPuppi",
        "description": "AK4PFPuppi Jet Identification TightLeptonVeto Criteria for Run3 Prompt2022CDE",
        "version": 1,
        "verbose_description": false,
        "eta_bin_edges": [0.0, 2.6, 2.7, 3.0, 5.0], 
        "criteria_expressions": [
            "CEMF<0.8 && CHM>0 && CHF>0.01 && NumConst>1 && NEMF<0.9 && MUF<0.8 && NHF<0.9",
            "CEMF<0.8 && NEMF<0.99 && MUF<0.8 && NHF<0.9",
            "NHF<0.9999",
            "NEMF<0.90 && NumNeutralParticle>2"
        ]
    },
    {
        "name": "JetID_Run3_Prompt2022CDE_Tight_AK4PFPuppi",
        "description": "AK4PFPuppi Jet Identification Tight Criteria for Run3 Prompt2022CDE",
        "version": 1,
        "verbose_description": false,
        "eta_bin_edges": [0.0, 2.6, 2.7, 3.0, 5.0], 
        "criteria_expressions": [
            "CHM>0 && CHF>0.01 && NumConst>1 && NEMF<0.9 && NHF<0.9",
            "NEMF<0.99 && NHF<0.9",
            "NHF<0.9999",
            "NEMF<0.90 && NumNeutralParticle>2"
        ]
    },
    {
        "name": "JetID_Run3_Prompt2022CDE_TightLeptonVeto_AK4PFCHS",
        "description": "AK4PFCHS Jet Identification TightLeptonVeto Criteria for Run3 Prompt2022CDE",
        "version": 1,
        "verbose_description": false,
        "eta_bin_edges": [0.0, 2.6, 2.7, 3.0, 5.0], 
        "criteria_expressions": [
            "CEMF<0.8 && CHM>0 && CHF>0.01 && NumConst>1 && NEMF<0.9 && MUF<0.8 && NHF<0.9",
            "CEMF<0.8 && CHM>0 && NEMF<0.99 && MUF<0.8 && NHF<0.9",
            "NEMF<0.99 && NumNeutralParticle>1",
            "NHF>0.2 && NEMF<0.90 && NumNeutralParticle>10"
        ]
    },
    {
        "name": "JetID_Run3_Prompt2022CDE_Tight_AK4PFCHS",
        "description": "AK4PFCHS Jet Identification Tight Criteria for Run3 Prompt2022CDE",
        "version": 1,
        "verbose_description": false,
        "eta_bin_edges": [0.0, 2.6, 2.7, 3.0, 5.0], 
        "criteria_expressions": [
            "CHM>0 && CHF>0.01 && NumConst>1 && NEMF<0.9 && NHF<0.9",
            "CHM>0 && NEMF<0.99 && NHF<0.9",
            "NEMF<0.99 && NumNeutralParticle>1",
            "NHF>0.2 && NEMF<0.90 && NumNeutralParticle>10"
        ]
    }
]
